user_config/__init__.py
user_config/ini.py
user_config-1.0a10.dist-info/DESCRIPTION.rst
user_config-1.0a10.dist-info/METADATA
user_config-1.0a10.dist-info/RECORD
user_config-1.0a10.dist-info/WHEEL
user_config-1.0a10.dist-info/entry_points.txt
user_config-1.0a10.dist-info/metadata.json
user_config-1.0a10.dist-info/top_level.txt
