Metadata-Version: 2.0
Name: user-config
Version: 1.0a10
Summary: manage user configuration for python packages
Home-page: https://github.com/nihlaeth/user_config
Author: nihlaeth
Author-email: info@nihlaeth.nl
License: GPLv3
Keywords: configuration config documentation ui ini
Platform: UNKNOWN
Classifier: Development Status :: 3 - Alpha
Classifier: Intended Audience :: Developers
Classifier: License :: OSI Approved :: GNU General Public License v3 (GPLv3)
Classifier: Operating System :: MacOS
Classifier: Operating System :: Microsoft :: Windows
Classifier: Operating System :: Unix
Classifier: Operating System :: POSIX
Classifier: Operating System :: POSIX :: Linux
Classifier: Programming Language :: Python
Classifier: Programming Language :: Python :: 2
Classifier: Programming Language :: Python :: 2.7
Classifier: Programming Language :: Python :: 3
Classifier: Programming Language :: Python :: 3.3
Classifier: Programming Language :: Python :: 3.4
Classifier: Programming Language :: Python :: 3.5
Classifier: Programming Language :: Python :: 3.6
Classifier: Topic :: Documentation
Classifier: Topic :: Software Development :: Documentation
Classifier: Topic :: Software Development :: Libraries
Classifier: Topic :: Software Development :: Libraries :: Python Modules
Classifier: Topic :: Software Development :: User Interfaces
Classifier: Topic :: Utilities
Requires-Python: >=2.7,!=3.0.*,!=3.1.*,!=3.2.*
Requires-Dist: appdirs (>=1.4)
Requires-Dist: pathlib; python_version <= "3.3"
Provides-Extra: deploy
Requires-Dist: codacy-coverage; extra == 'deploy'
Requires-Dist: coverage; extra == 'deploy'
Requires-Dist: pytest; extra == 'deploy'
Requires-Dist: pytest-cov; extra == 'deploy'
Requires-Dist: twine (>=1.8.1); extra == 'deploy'
Requires-Dist: wheel; extra == 'deploy'
Provides-Extra: doc
Requires-Dist: collective.checkdocs; extra == 'doc'
Requires-Dist: sphinx (>=1.3.1); extra == 'doc'
Requires-Dist: sphinx-pypi-upload; extra == 'doc'
Requires-Dist: sphinx-rtd-theme; extra == 'doc'
Provides-Extra: doctest
Requires-Dist: sphinx (>=1.3.1); extra == 'doctest'
